inference_client/__init__.py
inference_client/client.py
daoai_inference_client-0.4.2.dist-info/LICENSE
daoai_inference_client-0.4.2.dist-info/METADATA
daoai_inference_client-0.4.2.dist-info/WHEEL
daoai_inference_client-0.4.2.dist-info/top_level.txt
daoai_inference_client-0.4.2.dist-info/RECORD
