Metadata-Version: 2.1
Name: daoai-inference-client
Version: 0.4.2
Summary: DaoAI inference client
Author-email: DaoAI Maintainer <dxu@daoai.com>
Classifier: Programming Language :: Python :: 3
Classifier: License :: OSI Approved :: MIT License
Requires-Python: >=3.8
License-File: LICENSE
Requires-Dist: requests >=2.20.0
